vkparse/__init__.py
vkparse/__main__.py
vkparse/driver/__init__.py
vkparse/driver/driver.py
vkparse/driver/json_driver.py
vkparse/models/__init__.py
vkparse/models/attachment.py
vkparse/models/author.py
vkparse/models/message.py
vkparse/parsers/__init__.py
vkparse/parsers/abstract_parser.py
vkparse/parsers/bs4_parser.py
vkparse/pipe.py
vkparse-0.1.1.dist-info/LICENSE
vkparse-0.1.1.dist-info/WHEEL
vkparse-0.1.1.dist-info/METADATA
vkparse-0.1.1.dist-info/RECORD
