Metadata-Version: 2.1
Name: vkparse
Version: 0.1.1
Summary: Convert VK GDPR dumps to JSON/CSV/SQLite3
License: MIT
Author: Matthew Nekirov
Author-email: matthew.nekirov@gmail.com
Requires-Python: >=3.10,<4.0
Classifier: License :: OSI Approved :: MIT License
Classifier: Programming Language :: Python :: 3
Classifier: Programming Language :: Python :: 3.10
Requires-Dist: beautifulsoup4 (>=4.11.2,<5.0.0)
